src/__init__.py
src/risk_config.py
src/server.py
src/version.py
src/clients/__init__.py
src/clients/base.py
src/clients/exceptions.py
src/clients/common/__init__.py
src/clients/common/alias.py
src/clients/common/client.py
src/clients/common/cluster.py
src/clients/common/data_stream.py
src/clients/common/document.py
src/clients/common/general.py
src/clients/common/index.py
src/tools/__init__.py
src/tools/alias.py
src/tools/cluster.py
src/tools/data_stream.py
src/tools/document.py
src/tools/general.py
src/tools/index.py
src/tools/register.py
elasticsearch_mcp_server_es9-2.0.18.dist-info/METADATA
elasticsearch_mcp_server_es9-2.0.18.dist-info/WHEEL
elasticsearch_mcp_server_es9-2.0.18.dist-info/entry_points.txt
elasticsearch_mcp_server_es9-2.0.18.dist-info/licenses/LICENSE
elasticsearch_mcp_server_es9-2.0.18.dist-info/RECORD
