Metadata-Version: 2.4
Name: elasticsearch-mcp-server-es9
Version: 2.0.18
Summary: MCP Server for interacting with Elasticsearch and OpenSearch
License:                                  Apache License
License-File: LICENSE
Requires-Python: >=3.10
Requires-Dist: anthropic==0.49.0
Requires-Dist: elasticsearch==9.0.0
Requires-Dist: fastmcp==2.8.0
Requires-Dist: mcp==1.9.2
Requires-Dist: opensearch-py==2.8.0
Requires-Dist: pydantic<2.12.0,>=2.11.0
Requires-Dist: python-dotenv==1.1.0
Requires-Dist: tomli-w==1.2.0
Requires-Dist: tomli==2.2.1
